ctyparser/__info__.py
ctyparser/__init__.py
ctyparser/__main__.py
ctyparser/bigcty.py
ctyparser/py.typed
ctyparser-2.2.1.dist-info/LICENSE
ctyparser-2.2.1.dist-info/METADATA
ctyparser-2.2.1.dist-info/WHEEL
ctyparser-2.2.1.dist-info/top_level.txt
ctyparser-2.2.1.dist-info/RECORD
