Metadata-Version: 2.1
Name: ctyparser
Version: 2.2.1
Summary: A CTY.DAT parser for modern amateur radio programs.
Home-page: https://github.com/miaowware/ctyparser
Author: classabbyamp, 0x5c
Author-email: dev@kb6.ee, dev@0x5c.io
License: MIT
Platform: UNKNOWN
Classifier: License :: OSI Approved :: MIT License
Classifier: Programming Language :: Python :: 3
Classifier: Programming Language :: Python :: 3.6
Classifier: Programming Language :: Python :: 3.7
Classifier: Programming Language :: Python :: 3.8
Classifier: Programming Language :: Python :: 3.9
Classifier: Programming Language :: Python :: 3.10
Classifier: Development Status :: 5 - Production/Stable
Classifier: Environment :: Console
Classifier: Intended Audience :: Developers
Classifier: Operating System :: OS Independent
Classifier: Topic :: Communications :: Ham Radio
License-File: LICENSE
Requires-Dist: feedparser
Requires-Dist: requests
